adder.v
// Adder circuit
// delay was removed when synthesized on FPGA
`define AND and #30
`define OR or #30
`define NOT not #10
`define XOR xor #30

module structuralFullAdder
(
    output sum,
    output carryout,
    input A,
    input B,
    input carryin
);
    wire AxorB;
    wire AxorBandC;
    wire AandB;

    `XOR AxorBgate(AxorB, A, B);
    `XOR AxorBxorCgate(sum, AxorB, carryin);
    `AND AandBgate(AandB,A,B);
    `AND AxorBandCgate(AxorBandC, AxorB, carryin);
    `OR  orgate(carryout, AxorBandC, AandB);

endmodule

module FullAdderbit
(
  output[31:0] sum,  // 2's complement sum of a and b
  output carryout,  // Carry out of the summation of a and b
  output overflow,  // True if the calculation resulted in an overflow
  input[31:0] a,     // First operand in 2's complement format
  input[31:0] b      // Second operand in 2's complement format
);
    wire carryin[30:0]; // Connect carry outs to carry ins
    wire carryoutXor;
    wire msbXor;
    wire nmsbXor;

    structuralFullAdder adder0(sum[0],carryin[0],a[0],b[0],1'b0);
    structuralFullAdder adder1(sum[1],carryin[1],a[1],b[1],carryin[0]);
    structuralFullAdder adder2(sum[2],carryin[2],a[2],b[2],carryin[1]);
    structuralFullAdder adder3(sum[3],carryin[3],a[3],b[3],carryin[2]);
    structuralFullAdder adder4(sum[4],carryin[4],a[4],b[4],carryin[3]);
    structuralFullAdder adder5(sum[5],carryin[5],a[5],b[5],carryin[4]);
    structuralFullAdder adder6(sum[6],carryin[6],a[6],b[6],carryin[5]);
    structuralFullAdder adder7(sum[7],carryin[7],a[7],b[7],carryin[6]);
    structuralFullAdder adder8(sum[8],carryin[8],a[8],b[8],carryin[7]);
    structuralFullAdder adder9(sum[9],carryin[9],a[9],b[9],carryin[8]);
    structuralFullAdder adder10(sum[10],carryin[10],a[10],b[10],carryin[9]);
    structuralFullAdder adder11(sum[11],carryin[11],a[11],b[11],carryin[10]);
    structuralFullAdder adder12(sum[12],carryin[12],a[12],b[12],carryin[11]);
    structuralFullAdder adder13(sum[13],carryin[13],a[13],b[13],carryin[12]);
    structuralFullAdder adder14(sum[14],carryin[14],a[14],b[14],carryin[13]);
    structuralFullAdder adder15(sum[15],carryin[15],a[15],b[15],carryin[14]);
    structuralFullAdder adder16(sum[16],carryin[16],a[16],b[16],carryin[15]);
    structuralFullAdder adder17(sum[17],carryin[17],a[17],b[17],carryin[16]);
    structuralFullAdder adder18(sum[18],carryin[18],a[18],b[18],carryin[17]);
    structuralFullAdder adder19(sum[19],carryin[19],a[19],b[19],carryin[18]);
    structuralFullAdder adder20(sum[20],carryin[20],a[20],b[20],carryin[19]);
    structuralFullAdder adder21(sum[21],carryin[21],a[21],b[21],carryin[20]);
    structuralFullAdder adder22(sum[22],carryin[22],a[22],b[22],carryin[21]);
    structuralFullAdder adder23(sum[23],carryin[23],a[23],b[23],carryin[22]);
    structuralFullAdder adder24(sum[24],carryin[24],a[24],b[24],carryin[23]);
    structuralFullAdder adder25(sum[25],carryin[25],a[25],b[25],carryin[24]);
    structuralFullAdder adder26(sum[26],carryin[26],a[26],b[26],carryin[25]);
    structuralFullAdder adder27(sum[27],carryin[27],a[27],b[27],carryin[26]);
    structuralFullAdder adder28(sum[28],carryin[28],a[28],b[28],carryin[27]);
    structuralFullAdder adder29(sum[29],carryin[29],a[29],b[29],carryin[28]);
    structuralFullAdder adder30(sum[30],carryin[30],a[30],b[30],carryin[29]);
    structuralFullAdder adder31(sum[31],carryout,a[31],b[31],carryin[30]);

    // An overflow has occured if the final carryout and the sum's
    // most significant bit are not the same, if you're not adding
    // a negative and positive number
    `XOR carryoutXorGate(carryoutXor,carryout,sum[31]);
    `XOR msbXorGate(msbXor, a[31], b[31]);
    `NOT nmsbXorGate(nmsbXor, msbXor);
    `AND overflowAndGate(overflow,nmsbXor,carryoutXor);
endmodule

adder.t.v
// Adder testbench
`timescale 1 ns / 1 ps
`include "adder.v"
`define DELAY 5000

module testFullAdder();
    reg[31:0] a;
    reg[31:0] b;
    wire[31:0] sum;
    wire overflow, carryout;

    FullAdderbit adder(sum, carryout, overflow, a, b);
// We can add -8 through +7
initial begin
  $dumpfile("adder.vcd");
  $dumpvars();
  $display("Four Bit Full Adder positive + positive Tests");
  $display(" A   |  B   | Sum  | Carryout | Overflow | Sum Exp | Carryout Exp | Overflow Exp");            // Prints header for truth table
  a = 32'b00000000000000000000000000000000; b = 32'b00000000000000000000000000000000; #`DELAY                                 // Set A and B, wait for update (#1)
  $display("%b | %b | %b |   %b      |    %b     |  0000   | 0            | 0", a, b, sum, carryout, overflow);
  a = 32'b11111111111111111111111111111111; b = 32'b00000000000000000000000000000000; #`DELAY                                 // Set A and B, wait for update (#1)
  $display("%b | %b | %b |   %b      |    %b     |  0001   | 0            | 0", a, b, sum, carryout, overflow);

end
//For hte 16 test cases, we want:
// two positive numbers added with and w/out overflow
// two negative numbers added with and w/out overflow
// A positive number added with and w/out overflow and Carryout
// There will always be overflow with positive and negative?



endmodule

adder.vcd
$date
	Sun Sep 30 13:25:02 2018
$end
$version
	Icarus Verilog
$end
$timescale
	1ps
$end
$scope module testFullAdder $end
$var wire 32 ! sum [31:0] $end
$var wire 1 " overflow $end
$var wire 1 # carryout $end
$var reg 32 $ a [31:0] $end
$var reg 32 % b [31:0] $end
$scope module adder $end
$var wire 32 & a [31:0] $end
$var wire 32 ' b [31:0] $end
$var wire 1 ( carryoutXor $end
$var wire 1 ) msbXor $end
$var wire 1 * nmsbXor $end
$var wire 1 " overflow $end
$var wire 32 + sum [31:0] $end
$var wire 1 # carryout $end
$scope module adder0 $end
$var wire 1 , A $end
$var wire 1 - AandB $end
$var wire 1 . AxorB $end
$var wire 1 / AxorBandC $end
$var wire 1 0 B $end
$var wire 1 1 carryin $end
$var wire 1 2 carryout $end
$var wire 1 3 sum $end
$upscope $end
$scope module adder1 $end
$var wire 1 4 A $end
$var wire 1 5 AandB $end
$var wire 1 6 AxorB $end
$var wire 1 7 AxorBandC $end
$var wire 1 8 B $end
$var wire 1 2 carryin $end
$var wire 1 9 carryout $end
$var wire 1 : sum $end
$upscope $end
$scope module adder10 $end
$var wire 1 ; A $end
$var wire 1 < AandB $end
$var wire 1 = AxorB $end
$var wire 1 > AxorBandC $end
$var wire 1 ? B $end
$var wire 1 @ carryout $end
$var wire 1 A sum $end
$var wire 1 B carryin $end
$upscope $end
$scope module adder11 $end
$var wire 1 C A $end
$var wire 1 D AandB $end
$var wire 1 E AxorB $end
$var wire 1 F AxorBandC $end
$var wire 1 G B $end
$var wire 1 @ carryin $end
$var wire 1 H carryout $end
$var wire 1 I sum $end
$upscope $end
$scope module adder12 $end
$var wire 1 J A $end
$var wire 1 K AandB $end
$var wire 1 L AxorB $end
$var wire 1 M AxorBandC $end
$var wire 1 N B $end
$var wire 1 H carryin $end
$var wire 1 O carryout $end
$var wire 1 P sum $end
$upscope $end
$scope module adder13 $end
$var wire 1 Q A $end
$var wire 1 R AandB $end
$var wire 1 S AxorB $end
$var wire 1 T AxorBandC $end
$var wire 1 U B $end
$var wire 1 O carryin $end
$var wire 1 V carryout $end
$var wire 1 W sum $end
$upscope $end
$scope module adder14 $end
$var wire 1 X A $end
$var wire 1 Y AandB $end
$var wire 1 Z AxorB $end
$var wire 1 [ AxorBandC $end
$var wire 1 \ B $end
$var wire 1 V carryin $end
$var wire 1 ] carryout $end
$var wire 1 ^ sum $end
$upscope $end
$scope module adder15 $end
$var wire 1 _ A $end
$var wire 1 ` AandB $end
$var wire 1 a AxorB $end
$var wire 1 b AxorBandC $end
$var wire 1 c B $end
$var wire 1 ] carryin $end
$var wire 1 d carryout $end
$var wire 1 e sum $end
$upscope $end
$scope module adder16 $end
$var wire 1 f A $end
$var wire 1 g AandB $end
$var wire 1 h AxorB $end
$var wire 1 i AxorBandC $end
$var wire 1 j B $end
$var wire 1 d carryin $end
$var wire 1 k carryout $end
$var wire 1 l sum $end
$upscope $end
$scope module adder17 $end
$var wire 1 m A $end
$var wire 1 n AandB $end
$var wire 1 o AxorB $end
$var wire 1 p AxorBandC $end
$var wire 1 q B $end
$var wire 1 k carryin $end
$var wire 1 r carryout $end
$var wire 1 s sum $end
$upscope $end
$scope module adder18 $end
$var wire 1 t A $end
$var wire 1 u AandB $end
$var wire 1 v AxorB $end
$var wire 1 w AxorBandC $end
$var wire 1 x B $end
$var wire 1 r carryin $end
$var wire 1 y carryout $end
$var wire 1 z sum $end
$upscope $end
$scope module adder19 $end
$var wire 1 { A $end
$var wire 1 | AandB $end
$var wire 1 } AxorB $end
$var wire 1 ~ AxorBandC $end
$var wire 1 !" B $end
$var wire 1 y carryin $end
$var wire 1 "" carryout $end
$var wire 1 #" sum $end
$upscope $end
$scope module adder2 $end
$var wire 1 $" A $end
$var wire 1 %" AandB $end
$var wire 1 &" AxorB $end
$var wire 1 '" AxorBandC $end
$var wire 1 (" B $end
$var wire 1 9 carryin $end
$var wire 1 )" carryout $end
$var wire 1 *" sum $end
$upscope $end
$scope module adder20 $end
$var wire 1 +" A $end
$var wire 1 ," AandB $end
$var wire 1 -" AxorB $end
$var wire 1 ." AxorBandC $end
$var wire 1 /" B $end
$var wire 1 "" carryin $end
$var wire 1 0" carryout $end
$var wire 1 1" sum $end
$upscope $end
$scope module adder21 $end
$var wire 1 2" A $end
$var wire 1 3" AandB $end
$var wire 1 4" AxorB $end
$var wire 1 5" AxorBandC $end
$var wire 1 6" B $end
$var wire 1 0" carryin $end
$var wire 1 7" carryout $end
$var wire 1 8" sum $end
$upscope $end
$scope module adder22 $end
$var wire 1 9" A $end
$var wire 1 :" AandB $end
$var wire 1 ;" AxorB $end
$var wire 1 <" AxorBandC $end
$var wire 1 =" B $end
$var wire 1 7" carryin $end
$var wire 1 >" carryout $end
$var wire 1 ?" sum $end
$upscope $end
$scope module adder23 $end
$var wire 1 @" A $end
$var wire 1 A" AandB $end
$var wire 1 B" AxorB $end
$var wire 1 C" AxorBandC $end
$var wire 1 D" B $end
$var wire 1 >" carryin $end
$var wire 1 E" carryout $end
$var wire 1 F" sum $end
$upscope $end
$scope module adder24 $end
$var wire 1 G" A $end
$var wire 1 H" AandB $end
$var wire 1 I" AxorB $end
$var wire 1 J" AxorBandC $end
$var wire 1 K" B $end
$var wire 1 E" carryin $end
$var wire 1 L" carryout $end
$var wire 1 M" sum $end
$upscope $end
$scope module adder25 $end
$var wire 1 N" A $end
$var wire 1 O" AandB $end
$var wire 1 P" AxorB $end
$var wire 1 Q" AxorBandC $end
$var wire 1 R" B $end
$var wire 1 L" carryin $end
$var wire 1 S" carryout $end
$var wire 1 T" sum $end
$upscope $end
$scope module adder26 $end
$var wire 1 U" A $end
$var wire 1 V" AandB $end
$var wire 1 W" AxorB $end
$var wire 1 X" AxorBandC $end
$var wire 1 Y" B $end
$var wire 1 S" carryin $end
$var wire 1 Z" carryout $end
$var wire 1 [" sum $end
$upscope $end
$scope module adder27 $end
$var wire 1 \" A $end
$var wire 1 ]" AandB $end
$var wire 1 ^" AxorB $end
$var wire 1 _" AxorBandC $end
$var wire 1 `" B $end
$var wire 1 Z" carryin $end
$var wire 1 a" carryout $end
$var wire 1 b" sum $end
$upscope $end
$scope module adder28 $end
$var wire 1 c" A $end
$var wire 1 d" AandB $end
$var wire 1 e" AxorB $end
$var wire 1 f" AxorBandC $end
$var wire 1 g" B $end
$var wire 1 a" carryin $end
$var wire 1 h" carryout $end
$var wire 1 i" sum $end
$upscope $end
$scope module adder29 $end
$var wire 1 j" A $end
$var wire 1 k" AandB $end
$var wire 1 l" AxorB $end
$var wire 1 m" AxorBandC $end
$var wire 1 n" B $end
$var wire 1 h" carryin $end
$var wire 1 o" carryout $end
$var wire 1 p" sum $end
$upscope $end
$scope module adder3 $end
$var wire 1 q" A $end
$var wire 1 r" AandB $end
$var wire 1 s" AxorB $end
$var wire 1 t" AxorBandC $end
$var wire 1 u" B $end
$var wire 1 )" carryin $end
$var wire 1 v" carryout $end
$var wire 1 w" sum $end
$upscope $end
$scope module adder30 $end
$var wire 1 x" A $end
$var wire 1 y" AandB $end
$var wire 1 z" AxorB $end
$var wire 1 {" AxorBandC $end
$var wire 1 |" B $end
$var wire 1 o" carryin $end
$var wire 1 }" carryout $end
$var wire 1 ~" sum $end
$upscope $end
$scope module adder31 $end
$var wire 1 !# A $end
$var wire 1 "# AandB $end
$var wire 1 ## AxorB $end
$var wire 1 $# AxorBandC $end
$var wire 1 %# B $end
$var wire 1 }" carryin $end
$var wire 1 # carryout $end
$var wire 1 &# sum $end
$upscope $end
$scope module adder4 $end
$var wire 1 '# A $end
$var wire 1 (# AandB $end
$var wire 1 )# AxorB $end
$var wire 1 *# AxorBandC $end
$var wire 1 +# B $end
$var wire 1 v" carryin $end
$var wire 1 ,# carryout $end
$var wire 1 -# sum $end
$upscope $end
$scope module adder5 $end
$var wire 1 .# A $end
$var wire 1 /# AandB $end
$var wire 1 0# AxorB $end
$var wire 1 1# AxorBandC $end
$var wire 1 2# B $end
$var wire 1 ,# carryin $end
$var wire 1 3# carryout $end
$var wire 1 4# sum $end
$upscope $end
$scope module adder6 $end
$var wire 1 5# A $end
$var wire 1 6# AandB $end
$var wire 1 7# AxorB $end
$var wire 1 8# AxorBandC $end
$var wire 1 9# B $end
$var wire 1 3# carryin $end
$var wire 1 :# carryout $end
$var wire 1 ;# sum $end
$upscope $end
$scope module adder7 $end
$var wire 1 <# A $end
$var wire 1 =# AandB $end
$var wire 1 ># AxorB $end
$var wire 1 ?# AxorBandC $end
$var wire 1 @# B $end
$var wire 1 :# carryin $end
$var wire 1 A# carryout $end
$var wire 1 B# sum $end
$upscope $end
$scope module adder8 $end
$var wire 1 C# A $end
$var wire 1 D# AandB $end
$var wire 1 E# AxorB $end
$var wire 1 F# AxorBandC $end
$var wire 1 G# B $end
$var wire 1 A# carryin $end
$var wire 1 H# carryout $end
$var wire 1 I# sum $end
$upscope $end
$scope module adder9 $end
$var wire 1 J# A $end
$var wire 1 K# AandB $end
$var wire 1 L# AxorB $end
$var wire 1 M# AxorBandC $end
$var wire 1 N# B $end
$var wire 1 H# carryin $end
$var wire 1 B carryout $end
$var wire 1 O# sum $end
$upscope $end
$upscope $end
$upscope $end
$enddefinitions $end
#0
$dumpvars
xO#
0N#
xM#
xL#
xK#
0J#
xI#
xH#
0G#
xF#
xE#
xD#
0C#
xB#
xA#
0@#
x?#
x>#
x=#
0<#
x;#
x:#
09#
x8#
x7#
x6#
05#
x4#
x3#
02#
x1#
x0#
x/#
0.#
x-#
x,#
0+#
x*#
x)#
x(#
0'#
x&#
0%#
x$#
x##
x"#
0!#
x~"
x}"
0|"
x{"
xz"
xy"
0x"
xw"
xv"
0u"
xt"
xs"
xr"
0q"
xp"
xo"
0n"
xm"
xl"
xk"
0j"
xi"
xh"
0g"
xf"
xe"
xd"
0c"
xb"
xa"
0`"
x_"
x^"
x]"
0\"
x["
xZ"
0Y"
xX"
xW"
xV"
0U"
xT"
xS"
0R"
xQ"
xP"
xO"
0N"
xM"
xL"
0K"
xJ"
xI"
xH"
0G"
xF"
xE"
0D"
xC"
xB"
xA"
0@"
x?"
x>"
0="
x<"
x;"
x:"
09"
x8"
x7"
06"
x5"
x4"
x3"
02"
x1"
x0"
0/"
x."
x-"
x,"
0+"
x*"
x)"
0("
x'"
x&"
x%"
0$"
x#"
x""
0!"
x~
x}
x|
0{
xz
xy
0x
xw
xv
xu
0t
xs
xr
0q
xp
xo
xn
0m
xl
xk
0j
xi
xh
xg
0f
xe
xd
0c
xb
xa
x`
0_
x^
x]
0\
x[
xZ
xY
0X
xW
xV
0U
xT
xS
xR
0Q
xP
xO
0N
xM
xL
xK
0J
xI
xH
0G
xF
xE
xD
0C
xB
xA
x@
0?
x>
x=
x<
0;
x:
x9
08
x7
x6
x5
04
x3
x2
01
00
x/
x.
x-
0,
bx +
x*
x)
x(
b0 '
b0 &
b0 %
b0 $
x#
x"
bx !
$end
#20000
0.
0-
06
05
0&"
0%"
0s"
0r"
0)#
0(#
00#
0/#
07#
06#
0>#
0=#
0E#
0D#
0L#
0K#
0=
0<
0E
0D
0L
0K
0S
0R
0Z
0Y
0a
0`
0h
0g
0o
0n
0v
0u
0}
0|
0-"
0,"
04"
03"
0;"
0:"
0B"
0A"
0I"
0H"
0P"
0O"
0W"
0V"
0^"
0]"
0e"
0d"
0l"
0k"
0z"
0y"
0##
0"#
0)
0/
#40000
bx0 !
bx0 +
03
07
0'"
0t"
0*#
01#
08#
0?#
0F#
0M#
0>
0F
0M
0T
0[
0b
0i
0p
0w
0~
0."
05"
0<"
0C"
0J"
0Q"
0X"
0_"
0f"
0m"
0{"
0$#
1*
02
#60000
09
0)"
0v"
0,#
03#
0:#
0A#
0H#
0B
0@
0H
0O
0V
0]
0d
0k
0r
0y
0""
00"
07"
0>"
0E"
0L"
0S"
0Z"
0a"
0h"
0o"
0}"
0#
bx00 !
bx00 +
0:
#80000
0*"
0w"
0-#
04#
0;#
0B#
0I#
0O#
0A
0I
0P
0W
0^
0e
0l
0s
0z
0#"
01"
08"
0?"
0F"
0M"
0T"
0["
0b"
0i"
0p"
0~"
b0 !
b0 +
0&#
#100000
0(
#120000
0"
#5000000
1,
14
1$"
1q"
1'#
1.#
15#
1<#
1C#
1J#
1;
1C
1J
1Q
1X
1_
1f
1m
1t
1{
1+"
12"
19"
1@"
1G"
1N"
1U"
1\"
1c"
1j"
1x"
1!#
b11111111111111111111111111111111 $
b11111111111111111111111111111111 &
#5020000
1.
16
1&"
1s"
1)#
10#
17#
1>#
1E#
1L#
1=
1E
1L
1S
1Z
1a
1h
1o
1v
1}
1-"
14"
1;"
1B"
1I"
1P"
1W"
1^"
1e"
1l"
1z"
1##
1)
#5040000
13
1:
1*"
1w"
1-#
14#
1;#
1B#
1I#
1O#
1A
1I
1P
1W
1^
1e
1l
1s
1z
1#"
11"
18"
1?"
1F"
1M"
1T"
1["
1b"
1i"
1p"
1~"
b11111111111111111111111111111111 !
b11111111111111111111111111111111 +
1&#
0*
#5060000
1(
